tapcap.py
tapcap-1.0.dist-info/LICENSE.txt
tapcap-1.0.dist-info/METADATA
tapcap-1.0.dist-info/WHEEL
tapcap-1.0.dist-info/entry_points.txt
tapcap-1.0.dist-info/top_level.txt
tapcap-1.0.dist-info/RECORD
