Metadata-Version: 2.1
Name: tapcap
Version: 1.0
Summary: A network packet tabularization tool
Home-page: https://github.com/mayakapoor/tapcap
Author: Maya Kapoor
Author-email: mkapoor1@uncc.edu
Project-URL: Bug Tracker, https://github.com/mayakapoor/tapcap/issues
Project-URL: Documentation, https://tapcap.readthedocs.io/en/latest/
Classifier: Programming Language :: Python :: 3
Classifier: License :: OSI Approved :: MIT License
Classifier: Operating System :: OS Independent
Requires-Python: >=3.6
License-File: LICENSE.txt
